jokesdb/__init__.py
jokesdb-0.1.2.dist-info/licenses/LICENSE
jokesdb-0.1.2.dist-info/METADATA
jokesdb-0.1.2.dist-info/WHEEL
jokesdb-0.1.2.dist-info/top_level.txt
jokesdb-0.1.2.dist-info/RECORD
