Metadata-Version: 2.4
Name: JokesDB
Version: 0.1.2
Summary: A simple Python module to fetch jokes from my website.
Author-email: Code2Craft <support@code2craft.xyz>
License: MIT License
Project-URL: Homepage, https://code2craft.xyz
Project-URL: Source, https://github.com/gamercristi11/JokesDB
Project-URL: Docs, https://code2craft.xyz/jokesdb/docs.html
Classifier: Programming Language :: Python :: 3
Classifier: License :: OSI Approved :: MIT License
Classifier: Operating System :: OS Independent
Requires-Python: >=3.6
License-File: LICENSE
Requires-Dist: requests
Dynamic: license-file
